[{
    "id": 1,
    "brand": "Ford",
    "model": "Freestar",
    "year": 2003,
    "price": 3293,
    "img": "https://i.ibb.co/8zT5NgP/ford-freestar.jpg",
    "stock": 6
  }, {
    "id": 2,
    "brand": "Pontiac",
    "model": "Firefly",
    "year": 1992,
    "price": 3088,
    "img": "https://i.ibb.co/7VkRgbV/pontiac-firefly.png",
    "stock": 3
  }, {
    "id": 3,
    "brand": "Mercedes-Benz",
    "model": "S-Class",
    "year": 2006,
    "price": 3358,
    "img": "https://i.ibb.co/26v8HQG/mercedes-sclass.jpg",
    "stock": 8
  }, {
    "id": 4,
    "brand": "Lexus",
    "model": "IS F",
    "year": 2009,
    "price": 3639,
    "img": "https://i.ibb.co/rZn8Qrn/lexus-isf.jpg",
    "stock": 13
  }, {
    "id": 5,
    "brand": "BMW",
    "model": "M Roadster",
    "year": 2006,
    "price": 3188,
    "img": "https://i.ibb.co/N2DGFG5/bmw-mroadster.jpg",
    "stock": 5
  }]